LICENSE
README.md
setup.py
src/pytorch_fxdt1/__init__.py
src/pytorch_fxdt1/__main__.py
src/pytorch_fxdt1/fxd_score.py
src/pytorch_fxdt1.egg-info/PKG-INFO
src/pytorch_fxdt1.egg-info/SOURCES.txt
src/pytorch_fxdt1.egg-info/dependency_links.txt
src/pytorch_fxdt1.egg-info/entry_points.txt
src/pytorch_fxdt1.egg-info/requires.txt
src/pytorch_fxdt1.egg-info/top_level.txt