Metadata-Version: 2.1
Name: pytorch-fxdt1
Version: 0.1
Summary: A package containing methods to compute FXD score and other popular metrics for Chest X-Rays.
Home-page: https://github.com/Akshayakayy/FXD_Score.git
Author: Akshaya Karthikeyan
Author-email: akshaya.karthikeyan@research.iiit.ac.in
License: MIT
Download-URL: https://github.com/Akshayakayy/FXD_Score/archive/refs/tags/0.1.tar.gz
Keywords: FXD,Evaluation metric,featurization
Platform: UNKNOWN
Classifier: Programming Language :: Python :: 3
Classifier: Programming Language :: Python :: 3.4
Classifier: Programming Language :: Python :: 3.5
Classifier: Programming Language :: Python :: 3.6
Classifier: License :: OSI Approved :: MIT License
Requires-Python: >=3.5
License-File: LICENSE
